pejmanai_msca/__init__.py
pejmanai_msca/gantt_chart.py
pejmanai_msca-0.0.3.dist-info/METADATA
pejmanai_msca-0.0.3.dist-info/WHEEL
pejmanai_msca-0.0.3.dist-info/top_level.txt
pejmanai_msca-0.0.3.dist-info/RECORD
