Metadata-Version: 2.1
Name: pejmanai_msca
Version: 0.0.3
Summary: A Python package that creates a high-quality Gantt chart to visualize project timelines, work packages, milestones, and deliverables
Home-page: https://github.com/arad1367/pejmanai_MSCA_gantt_chart_pypi_package
Author: Pejman
Author-email: pejman.ebrahimi77@gmail.com
Project-URL: Source, https://github.com/arad1367/pejmanai_MSCA_gantt_chart_pypi_package
Project-URL: Buy me a coffee, https://ko-fi.com/arad1367
Classifier: Development Status :: 3 - Alpha
Classifier: Intended Audience :: Developers
Classifier: License :: OSI Approved :: MIT License
Classifier: Programming Language :: Python :: 3
Classifier: Programming Language :: Python :: 3.8
Classifier: Programming Language :: Python :: 3.9
Classifier: Programming Language :: Python :: 3.10
Classifier: Programming Language :: Python :: 3.11
Classifier: Programming Language :: Python :: 3.12
Requires-Python: >=3.8
Requires-Dist: plotly
Requires-Dist: kaleido
Requires-Dist: numpy
